LICENSE
README.md
setup.cfg
setup.py
render_psam/__init__.py
render_psam.egg-info/PKG-INFO
render_psam.egg-info/SOURCES.txt
render_psam.egg-info/dependency_links.txt
render_psam.egg-info/requires.txt
render_psam.egg-info/top_level.txt
tests/__init__.py
tests/test_render_psam.py